spiderlib/__init__.py
spiderlib/bak.py
spiderlib/test01.py
spiderlib/test02.py
spiderlib/test03.py
spiderlib/test04.py
spiderlib/test05.py
spiderlibs-0.0.13.dist-info/LICENSE
spiderlibs-0.0.13.dist-info/METADATA
spiderlibs-0.0.13.dist-info/WHEEL
spiderlibs-0.0.13.dist-info/top_level.txt
spiderlibs-0.0.13.dist-info/RECORD
